p1zyq-0.1.0.dist-info/METADATA
p1zyq-0.1.0.dist-info/WHEEL
p1zyq-0.1.0.dist-info/entry_points.txt
p1zyq-0.1.0.dist-info/licenses/LICENSE
p1zyq/__init__.py
p1zyq/_version.py
p1zyq/cli.py
p1zyq/main.py
p1zyq/p1zyq.py
p1zyq/utils/__init__.py
p1zyq/utils/data_utils.py
p1zyq/utils/file_utils.py
p1zyq/utils/logging_utils.py
p1zyq-0.1.0.dist-info/RECORD
