Metadata-Version: 2.1
Name: p1zyq
Version: 0.1.0
Summary: Python项目模板，包含创建Python包所需的所有基础结构。
Author-Email: Zhou Yuanqi <zyq1034378361@gmail.com>
Maintainer-Email: Zhou Yuanqi <zyq1034378361@gmail.com>
License: MIT License
Classifier: Development Status :: 3 - Alpha
Classifier: Intended Audience :: Developers
Classifier: License :: OSI Approved :: MIT License
Classifier: Natural Language :: English
Classifier: Programming Language :: Python :: 3
Classifier: Programming Language :: Python :: 3.10
Classifier: Programming Language :: Python :: 3.11
Classifier: Programming Language :: Python :: 3.12
Project-URL: Homepage, https://github.com/1034378361/p1zyq
Project-URL: Bug Tracker, https://github.com/1034378361/p1zyq/issues
Project-URL: Documentation, https://p1zyq.readthedocs.io/
Project-URL: Repository, https://github.com/1034378361/p1zyq
Project-URL: Changelog, https://github.com/1034378361/p1zyq/blob/main/CHANGELOG.md
Requires-Python: >=3.10
Requires-Dist: typer>=0.9.0
Requires-Dist: rich>=10.0.0
Provides-Extra: dev
Requires-Dist: pre-commit>=3.5.0; extra == "dev"
Requires-Dist: ipython>=8.18.0; extra == "dev"
Requires-Dist: ipdb>=0.13.13; extra == "dev"
Requires-Dist: python-dotenv>=1.0.0; extra == "dev"
Requires-Dist: gitpython>=3.1.40; extra == "dev"
Requires-Dist: bump2version>=1.0.1; extra == "dev"
Provides-Extra: test
Requires-Dist: pytest>=7.0.0; extra == "test"
Requires-Dist: pytest-cov>=4.1.0; extra == "test"
Requires-Dist: coverage>=7.2.0; extra == "test"
Requires-Dist: pytest-mock>=3.12.0; extra == "test"
Requires-Dist: tox>=4.11.0; extra == "test"
Requires-Dist: pytest-xdist>=3.5.0; extra == "test"
Provides-Extra: lint
Requires-Dist: ruff>=0.3.0; extra == "lint"
Requires-Dist: bandit>=1.7.5; extra == "lint"
Provides-Extra: typing
Requires-Dist: mypy>=1.6.0; extra == "typing"
Requires-Dist: types-requests>=2.31.0; extra == "typing"
Requires-Dist: types-pyyaml>=6.0.0; extra == "typing"
Provides-Extra: docs
Requires-Dist: mkdocs>=1.5.0; extra == "docs"
Requires-Dist: mkdocs-material>=9.4.0; extra == "docs"
Requires-Dist: mkdocstrings>=0.24.0; extra == "docs"
Requires-Dist: mkdocstrings-python>=1.8.0; extra == "docs"
Requires-Dist: mkdocs-git-revision-date-localized-plugin>=1.2.0; extra == "docs"
Provides-Extra: changelog
Requires-Dist: gitpython>=3.1.40; extra == "changelog"
Requires-Dist: pyyaml>=6.0.0; extra == "changelog"
Requires-Dist: yaml; extra == "changelog"
Provides-Extra: full-dev
Requires-Dist: dev; extra == "full-dev"
Requires-Dist: test; extra == "full-dev"
Requires-Dist: lint; extra == "full-dev"
Requires-Dist: typing; extra == "full-dev"
Requires-Dist: docs; extra == "full-dev"
Requires-Dist: changelog; extra == "full-dev"
